TexSoup/__init__.py
TexSoup/data.py
TexSoup/reader.py
TexSoup/tex.py
TexSoup/utils.py
TexSoup-0.2.0.dist-info/LICENSE
TexSoup-0.2.0.dist-info/METADATA
TexSoup-0.2.0.dist-info/WHEEL
TexSoup-0.2.0.dist-info/top_level.txt
TexSoup-0.2.0.dist-info/RECORD
